Workbook

Sheet 2026-01-01 to 2026-01-31
A1: SLERP.
AJ2: Slerp Limited (10222686)
A7: STATEMENT - WING SHACK CO
A8: January 1 to January 31
A9: Generated on: 14 February 2026
A10: Summary | M10: Order Summary - Count of Transactions by Type (after refunds)
B11: Gross Transaction Value (before refunds) | C11: =H90+H101+H105
B12: Gross Transaction Value (after refunds) | C12: =I90+I105 | N12: Pickup | O12: Delivery | P12: Total
B13: Fees & Charges | M13: ASAP | N13: =COUNTIFS(D21:D89, "Pickup", E21:E89, "ASAP") | O13: =COUNTIFS(D21:D89, "Delivery", E21:E89, "ASAP") | P13: =N13+O13
B14: Slerp Commissions (inc. VAT) | C14: =AF90+AF105 | M14: Scheduled Same-Day | N14: =COUNTIFS(D21:D89, "Pickup", E21:E89, "Scheduled same day") | O14: =COUNTIFS(D21:D89, "Delivery", E21:E89, "Scheduled same day") | P14: =N14+O14
B15: Slerp Courier Partner Fees (inc. VAT) | C15: =S90+S105 | M15: Pre-Order | N15: =COUNTIFS(D21:D89, "Pickup", E21:E89, "Preorder") | O15: =COUNTIFS(D21:D89, "Delivery", E21:E89, "Preorder") | P15: =N15+O15
B16: Payment Fees | C16: =AH90+AH101+AH105 | M16: Total | N16: =SUM(N13:N15) | O16: =SUM(O13:O15) | P16: =SUM(P13:P15)
B17: Net Payable | C17: =C12+SUM(C14:C16)
A19: Completed orders
A20: Order Date | B20: Fulfillment date | C20: Location name | D20: Fulfillment type | E20: Order type | F20: Status | G20: Slerp ref (Id) | H20: Gross transaction value | I20: Gross Transaction value (after refunds) | J20: Product total | K20: Product VAT component | L20: Product discount applied | M20: Product total after discounts (GMV)** | N20: Gifting charge | O20: Additional store fee | P20: VAT component of Additional store fee | Q20: Tips | R20: Refunds | S20: (A) Slerp Courier Partner Quoted Courier Fee Including Vat | T20: VAT component of Slerp Courier Partner Quoted Courier Fee | U20: Self-delivery Fee / Self-organised Fee including VAT | V20: VAT component of Self-delivery / Self-organised fee | W20: Delivery fees (charged to customer) pre-discount applied | X20: Delivery Subsidisation (charged to partner) pre-discount applied | Y20: Discount code | Z20: Delivery fee discount applied | AA20: Tiered Delivery pricing percent % | AB20: Tiered Delivery actual | AC20: Delivery fees (charged to customer) post-discount applied | AD20: VAT component of Delivery fees (charged to customer) post-discount applied | AE20: Delivery Subsidisation (charged to partner) post-discount applied | AF20: (B) Slerp Commission including VAT | AG20: VAT component of Slerp Commission | AH20: (C) Payment fee | AI20: Total Captured by Slerp (A) + (B) + (C) | AJ20: Notes | AK20: Courier reference | AL20: Stripe payment reference | AM20: Balance transaction (Id) | AN20: Courier Type
A21: 02/01/2026 | B21: 02/01/2026 | C21: Loughton | D21: Pickup | E21: Scheduled same day | F21: fulfilled | G21: AQGDP4 | H21: 18.45 | I21: 18.45 | J21: 18.45 | K21: 0 | L21: 0 | M21: 18.45 | N21: 0 | O21: 0 | P21: 0 | Q21: 0 | R21: 0 | S21: 0 | T21: 0 | U21: 0 | V21: 0 | W21: 0 | X21: 0 | Z21: 0 | AA21: 0 | AB21: 0 | AC21: 0 | AD21: 0 | AE21: 0 | AF21: -4.43 | AG21: 0.74 | AH21: -0.74 | AI21: -5.17 | AL21: ch_3SlDeSGOs2bxG0Rw0OVBE8j3 | AM21: txn_3SlDeSGOs2bxG0Rw0Mp3wN7X | AN21: Self Delivery / 3PL
A22: 02/01/2026 | B22: 02/01/2026 | C22: Loughton | D22: Pickup | E22: ASAP | F22: fulfilled | G22: KTKFFZ | H22: 35.3 | I22: 35.3 | J22: 43.3 | K22: 0 | L22: -8 | M22: 35.3 | N22: 0 | O22: 0 | P22: 0 | Q22: 0 | R22: 0 | S22: 0 | T22: 0 | U22: 0 | V22: 0 | W22: 0 | X22: 0 | Y22: JAN2026 | Z22: 0 | AA22: 0 | AB22: 0 | AC22: 0 | AD22: 0 | AE22: 0 | AF22: -8.48 | AG22: 1.41 | AH22: -0.69 | AI22: -9.17 | AL22: ch_3SlE1tGOs2bxG0Rw03RpiBCN | AM22: txn_3SlE1tGOs2bxG0Rw0mOj4A0C | AN22: Self Delivery / 3PL
A23: 03/01/2026 | B23: 03/01/2026 | C23: Loughton | D23: Delivery | E23: Scheduled same day | F23: fulfilled | G23: 6XQPK5 | H23: 32.29 | I23: 32.29 | J23: 32.3 | K23: 0 | L23: -8 | M23: 24.3 | N23: 0 | O23: 0 | P23: 0 | Q23: 0 | R23: 0 | S23: -15.6 | T23: 2.6 | U23: 0 | V23: 0 | W23: 7.99 | X23: 7.61 | Y23: JAN2026 | Z23: 0 | AA23: 0 | AB23: 0 | AC23: 7.99 | AD23: 1.33 | AE23: 7.61 | AF23: -5.84 | AG23: 0.97 | AH23: -0.65 | AI23: -22.09 | AK23: 6992701b-6fcc-417c-b36d-e0d910f5feae | AL23: ch_3SlVvtGOs2bxG0Rw1AYNb4D9 | AM23: txn_3SlVvtGOs2bxG0Rw1h9DthKq | AN23: Slerp Courier Partner - Bike/Moped
A24: 04/01/2026 | B24: 04/01/2026 | C24: Loughton | D24: Pickup | E24: ASAP | F24: fulfilled | G24: G6W6Z4 | H24: 15.3 | I24: 15.3 | J24: 15.3 | K24: 0 | L24: 0 | M24: 15.3 | N24: 0 | O24: 0 | P24: 0 | Q24: 0 | R24: 0 | S24: 0 | T24: 0 | U24: 0 | V24: 0 | W24: 0 | X24: 0 | Z24: 0 | AA24: 0 | AB24: 0 | AC24: 0 | AD24: 0 | AE24: 0 | AF24: -3.68 | AG24: 0.61 | AH24: -0.41 | AI24: -4.09 | AL24: ch_3SlwFCGOs2bxG0Rw0F1XpcsO | AM24: txn_3SlwFCGOs2bxG0Rw0OCfxso9 | AN24: Self Delivery / 3PL
A25: 05/01/2026 | B25: 05/01/2026 | C25: Loughton | D25: Delivery | E25: ASAP | F25: fulfilled | G25: J6V4CK | H25: 33.49 | I25: 33.49 | J25: 30.5 | K25: 0 | L25: 0 | M25: 30.5 | N25: 0 | O25: 0 | P25: 0 | Q25: 0 | R25: 0 | S25: -8.82 | T25: 1.47 | U25: 0 | V25: 0 | W25: 2.99 | X25: 5.83 | Z25: 0 | AA25: 0 | AB25: 0 | AC25: 2.99 | AD25: 0.5 | AE25: 5.83 | AF25: -7.32 | AG25: 1.22 | AH25: -0.67 | AI25: -16.81 | AK25: 879abacc-29de-4a61-9910-175a2998e24c | AL25: ch_3SmIxyGOs2bxG0Rw1pmHFmZ1 | AM25: txn_3SmIxyGOs2bxG0Rw17TIukLs | AN25: Slerp Courier Partner - Bike/Moped
A26: 05/01/2026 | B26: 05/01/2026 | C26: Loughton | D26: Pickup | E26: ASAP | F26: fulfilled | G26: GT2CD6 | H26: 14 | I26: 14 | J26: 19 | K26: 0 | L26: -5 | M26: 14 | N26: 0 | O26: 0 | P26: 0 | Q26: 0 | R26: 0 | S26: 0 | T26: 0 | U26: 0 | V26: 0 | W26: 0 | X26: 0 | Y26: AFLAK2 | Z26: 0 | AA26: 0 | AB26: 0 | AC26: 0 | AD26: 0 | AE26: 0 | AF26: -3.36 | AG26: 0.56 | AH26: -0.4 | AI26: -3.76 | AL26: ch_3SmJRqGOs2bxG0Rw0PArymok | AM26: txn_3SmJRqGOs2bxG0Rw06xFWItU | AN26: Self Delivery / 3PL
A27: 06/01/2026 | B27: 06/01/2026 | C27: Chatham | D27: Delivery | E27: ASAP | F27: fulfilled | G27: NGGC5J | H27: 38.08 | I27: 38.08 | J27: 39.1 | K27: 0 | L27: -6.5 | M27: 32.6 | N27: 0 | O27: 1.49 | P27: 0.25 | Q27: 0 | R27: 0 | S27: -9.66 | T27: 1.61 | U27: 0 | V27: 0 | W27: 3.99 | X27: 5.67 | Y27: CRISPY6 | Z27: 0 | AA27: 0 | AB27: 0 | AC27: 3.99 | AD27: 0.66 | AE27: 5.67 | AF27: -7.83 | AG27: 1.3 | AH27: -0.73 | AI27: -18.22 | AK27: 65279e13-6864-4fe4-8011-ebc8e28c6f09 | AL27: ch_3SmdjJGOs2bxG0Rw08uchZ73 | AM27: txn_3SmdjJGOs2bxG0Rw0QAZpkQc | AN27: Slerp Courier Partner - Bike/Moped
A28: 07/01/2026 | B28: 07/01/2026 | C28: Loughton | D28: Delivery | E28: Scheduled same day | F28: fulfilled | G28: JBZ5EZ | H28: 24.73 | I28: 24.73 | J28: 17.75 | K28: 0 | L28: 0 | M28: 17.75 | N28: 0 | O28: 0.99 | P28: 0.16 | Q28: 0 | R28: 0 | S28: -11.34 | T28: 1.89 | U28: 0 | V28: 0 | W28: 5.99 | X28: 5.35 | Z28: 0 | AA28: 0 | AB28: 0 | AC28: 5.99 | AD28: 1 | AE28: 5.35 | AF28: -4.26 | AG28: 0.71 | AH28: -0.55 | AI28: -16.15 | AK28: fda9cb8e-cbb0-47ec-8d30-b54ee1e0990a | AL28: ch_3SmwM8GOs2bxG0Rw1DO0LVvm | AM28: txn_3SmwM8GOs2bxG0Rw15acbBwd | AN28: Slerp Courier Partner - Bike/Moped
A29: 07/01/2026 | B29: 07/01/2026 | C29: Loughton | D29: Pickup | E29: Scheduled same day | F29: fulfilled | G29: ADHFZQ | H29: 11.74 | I29: 11.74 | J29: 10.75 | K29: 0.02519685 | L29: 0 | M29: 10.75 | N29: 0 | O29: 0.99 | P29: 0.16 | Q29: 0 | R29: 0 | S29: 0 | T29: 0 | U29: 0 | V29: 0 | W29: 0 | X29: 0 | Z29: 0 | AA29: 0 | AB29: 0 | AC29: 0 | AD29: 0 | AE29: 0 | AF29: -2.58 | AG29: 0.43 | AH29: -0.36 | AI29: -2.94 | AL29: ch_3Sn0FmGOs2bxG0Rw0tJByc7N | AM29: txn_3Sn0FmGOs2bxG0Rw05JLiXL2 | AN29: Self Delivery / 3PL
A30: 07/01/2026 | B30: 07/01/2026 | C30: Loughton | D30: Delivery | E30: Scheduled same day | F30: fulfilled | G30: YRUGXW | H30: 15.63 | I30: 15.63 | J30: 11.65 | K30: 0 | L30: 0 | M30: 11.65 | N30: 0 | O30: 0.99 | P30: 0.16 | Q30: 0 | R30: 0 | S30: -7.98 | T30: 1.33 | U30: 0 | V30: 0 | W30: 2.99 | X30: 4.99 | Z30: 0 | AA30: 0 | AB30: 0 | AC30: 2.99 | AD30: 0.5 | AE30: 4.99 | AF30: -2.8 | AG30: 0.47 | AH30: -0.42 | AI30: -11.2 | AK30: 431dd96a-01f8-4bb5-8ecd-aa742bd887ce | AL30: ch_3Sn1UNGOs2bxG0Rw0WDragVp | AM30: txn_3Sn1UNGOs2bxG0Rw0rkCnysi | AN30: Slerp Courier Partner - Car/Van
A31: 07/01/2026 | B31: 07/01/2026 | C31: Loughton | D31: Pickup | E31: ASAP | F31: fulfilled | G31: HCW5QM | H31: 39.29 | I31: 39.29 | J31: 43.3 | K31: 0 | L31: -5 | M31: 38.3 | N31: 0 | O31: 0.99 | P31: 0.16 | Q31: 0 | R31: 0 | S31: 0 | T31: 0 | U31: 0 | V31: 0 | W31: 0 | X31: 0 | Y31: AQ3M6K | Z31: 0 | AA31: 0 | AB31: 0 | AC31: 0 | AD31: 0 | AE31: 0 | AF31: -9.2 | AG31: 1.53 | AH31: -0.75 | AI31: -9.95 | AL31: ch_3Sn1inGOs2bxG0Rw0Fgn08tn | AM31: txn_3Sn1inGOs2bxG0Rw0pAwUQDp | AN31: Self Delivery / 3PL
A32: 07/01/2026 | B32: 07/01/2026 | C32: Loughton | D32: Delivery | E32: ASAP | F32: fulfilled | G32: ATGQXV | H32: 19.63 | I32: 19.63 | J32: 15.65 | K32: 0 | L32: 0 | M32: 15.65 | N32: 0 | O32: 0.99 | P32: 0.16 | Q32: 0 | R32: 0 | S32: -7.98 | T32: 1.33 | U32: 0 | V32: 0 | W32: 2.99 | X32: 4.99 | Z32: 0 | AA32: 0 | AB32: 0 | AC32: 2.99 | AD32: 0.5 | AE32: 4.99 | AF32: -3.76 | AG32: 0.63 | AH32: -0.47 | AI32: -12.21 | AK32: d96c4a04-9d4c-435a-af05-c9e8843306d5 | AL32: ch_3Sn1sIGOs2bxG0Rw1zqT9Ar3 | AM32: txn_3Sn1sIGOs2bxG0Rw1A27EZuz | AN32: Slerp Courier Partner - Bike/Moped
A33: 07/01/2026 | B33: 07/01/2026 | C33: Loughton | D33: Delivery | E33: ASAP | F33: fulfilled | G33: AGQCW3 | H33: 29.98 | I33: 29.98 | J33: 32.5 | K33: 0 | L33: -6.5 | M33: 26 | N33: 0 | O33: 0.99 | P33: 0.16 | Q33: 0 | R33: 0 | S33: -7.98 | T33: 1.33 | U33: 0 | V33: 0 | W33: 2.99 | X33: 4.99 | Y33: CRISPY6 | Z33: 0 | AA33: 0 | AB33: 0 | AC33: 2.99 | AD33: 0.5 | AE33: 4.99 | AF33: -6.24 | AG33: 1.04 | AH33: -0.62 | AI33: -14.84 | AK33: e5e46ba8-8a46-48f0-8e40-8a2338c15ce8 | AL33: ch_3Sn1vsGOs2bxG0Rw0Tm8i6nv | AM33: txn_3Sn1vsGOs2bxG0Rw06YB7u3B | AN33: Slerp Courier Partner - Bike/Moped
A34: 07/01/2026 | B34: 07/01/2026 | C34: Loughton | D34: Delivery | E34: ASAP | F34: fulfilled | G34: XRU7PR | H34: 23.48 | I34: 23.48 | J34: 22.95 | K34: 0 | L34: -3.45 | M34: 19.5 | N34: 0 | O34: 0.99 | P34: 0.16 | Q34: 0 | R34: 0 | S34: -7.98 | T34: 1.33 | U34: 0 | V34: 0 | W34: 2.99 | X34: 4.99 | Y34: H66ADR | Z34: 0 | AA34: 0 | AB34: 0 | AC34: 2.99 | AD34: 0.5 | AE34: 4.99 | AF34: -4.68 | AG34: 0.78 | AH34: -0.53 | AI34: -13.19 | AK34: ef938c78-c2a3-446e-a45e-4b62e09c5914 | AL34: ch_3Sn2NnGOs2bxG0Rw1rSVHlrx | AM34: txn_3Sn2NnGOs2bxG0Rw1dJQtPiE | AN34: Slerp Courier Partner - Bike/Moped
A35: 07/01/2026 | B35: 07/01/2026 | C35: Loughton | D35: Pickup | E35: ASAP | F35: fulfilled | G35: QTV7GG | H35: 14.94 | I35: 14.94 | J35: 13.95 | K35: 0 | L35: 0 | M35: 13.95 | N35: 0 | O35: 0.99 | P35: 0.16 | Q35: 0 | R35: 0 | S35: 0 | T35: 0 | U35: 0 | V35: 0 | W35: 0 | X35: 0 | Z35: 0 | AA35: 0 | AB35: 0 | AC35: 0 | AD35: 0 | AE35: 0 | AF35: -3.35 | AG35: 0.56 | AH35: -0.41 | AI35: -3.76 | AL35: ch_3Sn2ORGOs2bxG0Rw0NKqG77T | AM35: txn_3Sn2ORGOs2bxG0Rw0DfVBbtF | AN35: Self Delivery / 3PL
A36: 08/01/2026 | B36: 08/01/2026 | C36: Loughton | D36: Pickup | E36: Scheduled same day | F36: fulfilled | G36: TPWY4Q | H36: 28.89 | I36: 28.89 | J36: 27.9 | K36: 0 | L36: 0 | M36: 27.9 | N36: 0 | O36: 0.99 | P36: 0.16 | Q36: 0 | R36: 0 | S36: 0 | T36: 0 | U36: 0 | V36: 0 | W36: 0 | X36: 0 | Z36: 0 | AA36: 0 | AB36: 0 | AC36: 0 | AD36: 0 | AE36: 0 | AF36: -6.7 | AG36: 1.12 | AH36: -0.6 | AI36: -7.3 | AL36: ch_3SnPMuGOs2bxG0Rw0vOmWcst | AM36: txn_3SnPMuGOs2bxG0Rw0zFMiLil | AN36: Self Delivery / 3PL
A37: 10/01/2026 | B37: 10/01/2026 | C37: Loughton | D37: Pickup | E37: ASAP | F37: fulfilled | G37: DLKEUX | H37: 23.44 | I37: 23.44 | J37: 30.45 | K37: 0 | L37: -8 | M37: 22.45 | N37: 0 | O37: 0.99 | P37: 0.16 | Q37: 0 | R37: 0 | S37: 0 | T37: 0 | U37: 0 | V37: 0 | W37: 0 | X37: 0 | Y37: SPEND30SAVE802 | Z37: 0 | AA37: 0 | AB37: 0 | AC37: 0 | AD37: 0 | AE37: 0 | AF37: -5.39 | AG37: 0.9 | AH37: -0.88 | AI37: -6.27 | AL37: ch_3So8MKGOs2bxG0Rw108qvya2 | AM37: txn_3So8MKGOs2bxG0Rw1YnoUkjQ | AN37: Self Delivery / 3PL
A38: 10/01/2026 | B38: 10/01/2026 | C38: Loughton | D38: Pickup | E38: Scheduled same day | F38: fulfilled | G38: ZP3U5F | H38: 24.29 | I38: 24.29 | J38: 31.3 | K38: 0 | L38: -8 | M38: 23.3 | N38: 0 | O38: 0.99 | P38: 0.16 | Q38: 0 | R38: 0 | S38: 0 | T38: 0 | U38: 0 | V38: 0 | W38: 0 | X38: 0 | Y38: SPEND30SAVE802 | Z38: 0 | AA38: 0 | AB38: 0 | AC38: 0 | AD38: 0 | AE38: 0 | AF38: -5.6 | AG38: 0.93 | AH38: -0.54 | AI38: -6.14 | AL38: ch_3So8bZGOs2bxG0Rw1KQX6TTp | AM38: txn_3So8bZGOs2bxG0Rw1swRHRx5 | AN38: Self Delivery / 3PL
A39: 11/01/2026 | B39: 11/01/2026 | C39: Loughton | D39: Pickup | E39: ASAP | F39: fulfilled | G39: CG3L6L | H39: 28.89 | I39: 28.89 | J39: 27.9 | K39: 0 | L39: 0 | M39: 27.9 | N39: 0 | O39: 0.99 | P39: 0.16 | Q39: 0 | R39: 0 | S39: 0 | T39: 0 | U39: 0 | V39: 0 | W39: 0 | X39: 0 | Z39: 0 | AA39: 0 | AB39: 0 | AC39: 0 | AD39: 0 | AE39: 0 | AF39: -6.7 | AG39: 1.12 | AH39: -0.6 | AI39: -7.3 | AL39: ch_3SoUl5GOs2bxG0Rw0QsgC5w5 | AM39: txn_3SoUl5GOs2bxG0Rw0vio2Mui | AN39: Self Delivery / 3PL
A40: 11/01/2026 | B40: 11/01/2026 | C40: Loughton | D40: Pickup | E40: ASAP | F40: fulfilled | G40: 2MPJ7B | H40: 8.44 | I40: 8.44 | J40: 13.95 | K40: 0 | L40: -6.5 | M40: 7.45 | N40: 0 | O40: 0.99 | P40: 0.16 | Q40: 0 | R40: 0 | S40: 0 | T40: 0 | U40: 0 | V40: 0 | W40: 0 | X40: 0 | Y40: CRISPY6 | Z40: 0 | AA40: 0 | AB40: 0 | AC40: 0 | AD40: 0 | AE40: 0 | AF40: -1.79 | AG40: 0.3 | AH40: -0.44 | AI40: -2.23 | AL40: ch_3SoV8hGOs2bxG0Rw19wz4noB | AM40: txn_3SoV8hGOs2bxG0Rw1V5n7cOy | AN40: Self Delivery / 3PL
A41: 11/01/2026 | B41: 11/01/2026 | C41: Loughton | D41: Pickup | E41: ASAP | F41: fulfilled | G41: GMGESW | H41: 25.84 | I41: 25.84 | J41: 32.85 | K41: 0 | L41: -8 | M41: 24.85 | N41: 0 | O41: 0.99 | P41: 0.16 | Q41: 0 | R41: 0 | S41: 0 | T41: 0 | U41: 0 | V41: 0 | W41: 0 | X41: 0 | Y41: SPEND30SAVE802 | Z41: 0 | AA41: 0 | AB41: 0 | AC41: 0 | AD41: 0 | AE41: 0 | AF41: -5.97 | AG41: 1 | AH41: -0.95 | AI41: -6.92 | AL41: ch_3SoVHtGOs2bxG0Rw0tAig5Dx | AM41: txn_3SoVHtGOs2bxG0Rw0CgEnyzu | AN41: Self Delivery / 3PL
A42: 12/01/2026 | B42: 12/01/2026 | C42: Loughton | D42: Pickup | E42: ASAP | F42: fulfilled | G42: 4PKYLR | H42: 14.89 | I42: 14.89 | J42: 18.9 | K42: 0 | L42: -5 | M42: 13.9 | N42: 0 | O42: 0.99 | P42: 0.16 | Q42: 0 | R42: 0 | S42: 0 | T42: 0 | U42: 0 | V42: 0 | W42: 0 | X42: 0 | Y42: RUUDTG | Z42: 0 | AA42: 0 | AB42: 0 | AC42: 0 | AD42: 0 | AE42: 0 | AF42: -3.34 | AG42: 0.56 | AH42: -0.41 | AI42: -3.75 | AL42: ch_3SopoxGOs2bxG0Rw0oYHRWpt | AM42: txn_3SopoxGOs2bxG0Rw0Ybjme2N | AN42: Self Delivery / 3PL
A43: 12/01/2026 | B43: 12/01/2026 | C43: Loughton | D43: Delivery | E43: ASAP | F43: fulfilled | G43: VJSJJW | H43: 18.88 | I43: 18.88 | J43: 14.9 | K43: 0 | L43: 0 | M43: 14.9 | N43: 0 | O43: 0.99 | P43: 0.16 | Q43: 0 | R43: 0 | S43: -8.82 | T43: 1.47 | U43: 0 | V43: 0 | W43: 2.99 | X43: 5.83 | Z43: 0 | AA43: 0 | AB43: 0 | AC43: 2.99 | AD43: 0.5 | AE43: 5.83 | AF43: -3.58 | AG43: 0.6 | AH43: -0.46 | AI43: -12.86 | AK43: cb32eb4f-6a0b-4373-bea6-32dfeeb8d325 | AL43: ch_3Soqj4GOs2bxG0Rw161lPm9x | AM43: txn_3Soqj4GOs2bxG0Rw1SU4tIo5 | AN43: Slerp Courier Partner - Car/Van
A44: 14/01/2026 | B44: 14/01/2026 | C44: Maidstone | D44: Pickup | E44: Scheduled same day | F44: fulfilled | G44: VZMNAW | H44: 13 | I44: 13 | J44: 13 | K44: 0 | L44: 0 | M44: 13 | N44: 0 | O44: 0 | P44: 0 | Q44: 0 | R44: 0 | S44: 0 | T44: 0 | U44: 0 | V44: 0 | W44: 0 | X44: 0 | Z44: 0 | AA44: 0 | AB44: 0 | AC44: 0 | AD44: 0 | AE44: 0 | AF44: -3.12 | AG44: 0.52 | AH44: -0.38 | AI44: -3.5 | AL44: ch_3SpTjCGOs2bxG0Rw1cg06jpR | AM44: txn_3SpTjCGOs2bxG0Rw1XOnUky2 | AN44: Self Delivery / 3PL
A45: 14/01/2026 | B45: 14/01/2026 | C45: Loughton | D45: Delivery | E45: Scheduled same day | F45: fulfilled | G45: JTKQPZ | H45: 19.98 | I45: 19.98 | J45: 17.75 | K45: 0 | L45: -4.75 | M45: 13 | N45: 0 | O45: 0.99 | P45: 0.16 | Q45: 0 | R45: 0 | S45: -11.34 | T45: 1.89 | U45: 0 | V45: 0 | W45: 5.99 | X45: 5.35 | Y45: Q7V2T7 | Z45: 0 | AA45: 0 | AB45: 0 | AC45: 5.99 | AD45: 1 | AE45: 5.35 | AF45: -3.12 | AG45: 0.52 | AH45: -0.48 | AI45: -14.94 | AK45: 850d4d22-002a-4eff-8d4f-013e9844ccd8 | AL45: ch_3SpTpBGOs2bxG0Rw15p1pdvu | AM45: txn_3SpTpBGOs2bxG0Rw1INIlsi3 | AN45: Slerp Courier Partner - Bike/Moped
A46: 14/01/2026 | B46: 14/01/2026 | C46: Loughton | D46: Pickup | E46: ASAP | F46: fulfilled | G46: VXAYJ5 | H46: 18.69 | I46: 18.69 | J46: 24.2 | K46: 0 | L46: -6.5 | M46: 17.7 | N46: 0 | O46: 0.99 | P46: 0.16 | Q46: 0 | R46: 0 | S46: 0 | T46: 0 | U46: 0 | V46: 0 | W46: 0 | X46: 0 | Y46: CRISPY6 | Z46: 0 | AA46: 0 | AB46: 0 | AC46: 0 | AD46: 0 | AE46: 0 | AF46: -4.25 | AG46: 0.71 | AH46: -0.46 | AI46: -4.71 | AL46: ch_3SpYbDGOs2bxG0Rw08S05uY7 | AM46: txn_3SpYbDGOs2bxG0Rw0ZeEAbU6 | AN46: Self Delivery / 3PL
A47: 14/01/2026 | B47: 14/01/2026 | C47: Loughton | D47: Pickup | E47: ASAP | F47: fulfilled | G47: CT6BQ7 | H47: 17.09 | I47: 17.09 | J47: 22.6 | K47: 0 | L47: -6.5 | M47: 16.1 | N47: 0 | O47: 0.99 | P47: 0.16 | Q47: 0 | R47: 0 | S47: 0 | T47: 0 | U47: 0 | V47: 0 | W47: 0 | X47: 0 | Y47: CRISPY6 | Z47: 0 | AA47: 0 | AB47: 0 | AC47: 0 | AD47: 0 | AE47: 0 | AF47: -3.87 | AG47: 0.64 | AH47: -0.44 | AI47: -4.31 | AL47: ch_3SpXnUGOs2bxG0Rw1geLxMKp | AM47: txn_3SpXnUGOs2bxG0Rw1EbH8eSs | AN47: Self Delivery / 3PL
A48: 14/01/2026 | B48: 14/01/2026 | C48: Loughton | D48: Pickup | E48: Scheduled same day | F48: fulfilled | G48: SJBGAY | H48: 14.94 | I48: 14.94 | J48: 20.45 | K48: 0 | L48: -6.5 | M48: 13.95 | N48: 0 | O48: 0.99 | P48: 0.16 | Q48: 0 | R48: 0 | S48: 0 | T48: 0 | U48: 0 | V48: 0 | W48: 0 | X48: 0 | Y48: CRISPY6 | Z48: 0 | AA48: 0 | AB48: 0 | AC48: 0 | AD48: 0 | AE48: 0 | AF48: -3.35 | AG48: 0.56 | AH48: -0.41 | AI48: -3.76 | AL48: ch_3SpYmsGOs2bxG0Rw0umE7114 | AM48: txn_3SpYmsGOs2bxG0Rw08bzW2yq | AN48: Self Delivery / 3PL
A49: 14/01/2026 | B49: 14/01/2026 | C49: Maidstone | D49: Delivery | E49: ASAP | F49: fulfilled | G49: TAZWGU | H49: 44.59 | I49: 44.59 | J49: 46.1 | K49: 0 | L49: -6.5 | M49: 39.6 | N49: 0 | O49: 0 | P49: 0 | Q49: 0 | R49: 0 | S49: 0 | T49: 0 | U49: -4.99 | V49: 0 | W49: 4.99 | X49: 0 | Y49: CRISPY6 | Z49: 0 | AA49: 0 | AB49: 0 | AC49: 4.99 | AD49: 0 | AE49: 0 | AF49: -9.51 | AG49: 1.58 | AH49: -0.82 | AI49: -10.33 | AK49: aa82e992-8d4c-46e8-a73f-e746b3f2faee | AL49: ch_3SpaxkGOs2bxG0Rw1TZDw0AP | AM49: txn_3SpaxkGOs2bxG0Rw1Yvt7ccb | AN49: Self Delivery / 3PL
A50: 14/01/2026 | B50: 14/01/2026 | C50: Loughton | D50: Delivery | E50: ASAP | F50: fulfilled | G50: BSDWNA | H50: 14.47 | I50: 14.47 | J50: 10.49 | K50: 0 | L50: 0 | M50: 10.49 | N50: 0 | O50: 0.99 | P50: 0.16 | Q50: 0 | R50: 0 | S50: -8.82 | T50: 1.47 | U50: 0 | V50: 0 | W50: 2.99 | X50: 5.83 | Z50: 0 | AA50: 0 | AB50: 0 | AC50: 2.99 | AD50: 0.5 | AE50: 5.83 | AF50: -2.52 | AG50: 0.42 | AH50: -0.4 | AI50: -11.74 | AK50: 2339bf0f-cfbf-4572-af13-fb183d917433 | AL50: ch_3SpbKbGOs2bxG0Rw0HCgpqn0 | AM50: txn_3SpbKbGOs2bxG0Rw0N8yFsVX | AN50: Slerp Courier Partner - Car/Van
A51: 16/01/2026 | B51: 16/01/2026 | C51: Loughton | D51: Delivery | E51: Scheduled same day | F51: fulfilled | G51: PMTPYD | H51: 14.98 | I51: 14.98 | J51: 17.5 | K51: 0 | L51: -6.5 | M51: 11 | N51: 0 | O51: 0.99 | P51: 0.16 | Q51: 0 | R51: 0 | S51: -8.82 | T51: 1.47 | U51: 0 | V51: 0 | W51: 2.99 | X51: 5.83 | Y51: CRISPY6 | Z51: 0 | AA51: 0 | AB51: 0 | AC51: 2.99 | AD51: 0.5 | AE51: 5.83 | AF51: -2.64 | AG51: 0.44 | AH51: -0.41 | AI51: -11.87 | AK51: d794a450-0d7b-4979-b9c8-3e39af205d13 | AL51: ch_3SqGWdGOs2bxG0Rw1Sox3dNh | AM51: txn_3SqGWdGOs2bxG0Rw1zdMkoqM | AN51: Slerp Courier Partner - Bike/Moped
A52: 16/01/2026 | B52: 16/01/2026 | C52: Loughton | D52: Delivery | E52: ASAP | F52: fulfilled | G52: 26QNC4 | H52: 38.53 | I52: 38.53 | J52: 40.05 | K52: 0 | L52: -6.5 | M52: 33.55 | N52: 0 | O52: 0.99 | P52: 0.16 | Q52: 1 | R52: 0 | S52: -7.98 | T52: 1.33 | U52: 0 | V52: 0 | W52: 2.99 | X52: 4.99 | Y52: CRISPY6 | Z52: 0 | AA52: 0 | AB52: 0 | AC52: 2.99 | AD52: 0.5 | AE52: 4.99 | AF52: -8.06 | AG52: 1.34 | AH52: -0.74 | AI52: -16.78 | AK52: e9ade47e-f683-4a78-8dc4-20ccb019b83d | AL52: ch_3SqIArGOs2bxG0Rw0IAfWHuu | AM52: txn_3SqIArGOs2bxG0Rw0R9Bsn07 | AN52: Slerp Courier Partner - Bike/Moped
A53: 16/01/2026 | B53: 16/01/2026 | C53: Loughton | D53: Pickup | E53: Scheduled same day | F53: fulfilled | G53: MCETFZ | H53: 24.89 | I53: 24.89 | J53: 23.9 | K53: 0 | L53: 0 | M53: 23.9 | N53: 0 | O53: 0.99 | P53: 0.16 | Q53: 0 | R53: 0 | S53: 0 | T53: 0 | U53: 0 | V53: 0 | W53: 0 | X53: 0 | Z53: 0 | AA53: 0 | AB53: 0 | AC53: 0 | AD53: 0 | AE53: 0 | AF53: -5.74 | AG53: 0.96 | AH53: -0.55 | AI53: -6.29 | AL53: ch_3SqKqfGOs2bxG0Rw0G7JXuo0 | AM53: txn_3SqKqfGOs2bxG0Rw0XlBrVgM | AN53: Self Delivery / 3PL
A54: 17/01/2026 | B54: 17/01/2026 | C54: Loughton | D54: Pickup | E54: ASAP | F54: fulfilled | G54: YN4YWM | H54: 21.64 | I54: 21.64 | J54: 27.15 | K54: 0 | L54: -6.5 | M54: 20.65 | N54: 0 | O54: 0.99 | P54: 0.16 | Q54: 0 | R54: 0 | S54: 0 | T54: 0 | U54: 0 | V54: 0 | W54: 0 | X54: 0 | Y54: CRISPY6 | Z54: 0 | AA54: 0 | AB54: 0 | AC54: 0 | AD54: 0 | AE54: 0 | AF54: -4.96 | AG54: 0.83 | AH54: -0.5 | AI54: -5.46 | AL54: ch_3SqZixGOs2bxG0Rw0d5ngiAV | AM54: txn_3SqZixGOs2bxG0Rw0ElxloMs | AN54: Self Delivery / 3PL
A55: 17/01/2026 | B55: 17/01/2026 | C55: Loughton | D55: Pickup | E55: ASAP | F55: fulfilled | G55: 4YCBS6 | H55: 16.14 | I55: 16.14 | J55: 21.65 | K55: 0 | L55: -6.5 | M55: 15.15 | N55: 0 | O55: 0.99 | P55: 0.16 | Q55: 0 | R55: 0 | S55: 0 | T55: 0 | U55: 0 | V55: 0 | W55: 0 | X55: 0 | Y55: CRISPY6 | Z55: 0 | AA55: 0 | AB55: 0 | AC55: 0 | AD55: 0 | AE55: 0 | AF55: -3.64 | AG55: 0.61 | AH55: -0.43 | AI55: -4.07 | AL55: ch_3SqZuoGOs2bxG0Rw084cyxTU | AM55: txn_3SqZuoGOs2bxG0Rw00jYqKxx | AN55: Self Delivery / 3PL
A56: 17/01/2026 | B56: 17/01/2026 | C56: Loughton | D56: Pickup | E56: ASAP | F56: fulfilled | G56: XSJ774 | H56: 16.9 | I56: 16.9 | J56: 21.65 | K56: 0 | L56: -6.5 | M56: 15.15 | N56: 0 | O56: 0.99 | P56: 0.16 | Q56: 0.76 | R56: 0 | S56: 0 | T56: 0 | U56: 0 | V56: 0 | W56: 0 | X56: 0 | Y56: CRISPY6 | Z56: 0 | AA56: 0 | AB56: 0 | AC56: 0 | AD56: 0 | AE56: 0 | AF56: -3.64 | AG56: 0.61 | AH56: -0.44 | AI56: -4.08 | AL56: ch_3SqZviGOs2bxG0Rw1PdpDYle | AM56: txn_3SqZviGOs2bxG0Rw1ueuXR1Q | AN56: Self Delivery / 3PL
A57: 17/01/2026 | B57: 17/01/2026 | C57: Maidstone | D57: Delivery | E57: ASAP | F57: fulfilled | G57: ZR2Q52 | H57: 32.99 | I57: 32.99 | J57: 36.5 | K57: 5 | L57: -6.5 | M57: 30 | N57: 0 | O57: 0 | P57: 0 | Q57: 0 | R57: 0 | S57: 0 | T57: 0 | U57: -2.99 | V57: 0 | W57: 2.99 | X57: 0 | Y57: CRISPY6 | Z57: 0 | AA57: 0 | AB57: 0 | AC57: 2.99 | AD57: 0 | AE57: 0 | AF57: -7.2 | AG57: 1.2 | AH57: -0.66 | AI57: -7.86 | AK57: 15132e91-6150-4405-92f4-0cff1ab4ad3b | AL57: ch_3SqcwXGOs2bxG0Rw1bsU9H2H | AM57: txn_3SqcwXGOs2bxG0Rw13AadIWw | AN57: Self Delivery / 3PL
A58: 18/01/2026 | B58: 18/01/2026 | C58: Loughton | D58: Delivery | E58: Scheduled same day | F58: fulfilled | G58: GFXPVQ | H58: 38.08 | I58: 38.08 | J58: 37.5 | K58: 0 | L58: -6.5 | M58: 31 | N58: 0 | O58: 0.99 | P58: 0.16 | Q58: 3.1 | R58: 0 | S58: -8.82 | T58: 1.47 | U58: 0 | V58: 0 | W58: 2.99 | X58: 5.83 | Y58: CRISPY6 | Z58: 0 | AA58: 0 | AB58: 0 | AC58: 2.99 | AD58: 0.5 | AE58: 5.83 | AF58: -7.44 | AG58: 1.24 | AH58: -0.73 | AI58: -16.99 | AK58: 84635c87-eba8-4024-b277-e3f75bc046c5 | AL58: ch_3SqzyCGOs2bxG0Rw0d3GYfHv | AM58: txn_3SqzyCGOs2bxG0Rw0I9E7gUf | AN58: Slerp Courier Partner - Bike/Moped
A59: 19/01/2026 | B59: 19/01/2026 | C59: Loughton | D59: Pickup | E59: Scheduled same day | F59: fulfilled | G59: 27WCYP | H59: 30.44 | I59: 30.44 | J59: 29.45 | K59: 0 | L59: 0 | M59: 29.45 | N59: 0 | O59: 0.99 | P59: 0.16 | Q59: 0 | R59: 0 | S59: 0 | T59: 0 | U59: 0 | V59: 0 | W59: 0 | X59: 0 | Z59: 0 | AA59: 0 | AB59: 0 | AC59: 0 | AD59: 0 | AE59: 0 | AF59: -7.07 | AG59: 1.18 | AH59: -0.63 | AI59: -7.7 | AL59: ch_3SrN8iGOs2bxG0Rw1LhgbdVb | AM59: txn_3SrN8iGOs2bxG0Rw1jv6QqCQ | AN59: Self Delivery / 3PL
A60: 19/01/2026 | B60: 19/01/2026 | C60: Maidstone | D60: Delivery | E60: ASAP | F60: fulfilled | G60: GVDAVT | H60: 37.84 | I60: 37.84 | J60: 34.85 | K60: 0 | L60: 0 | M60: 34.85 | N60: 0 | O60: 0 | P60: 0 | Q60: 0 | R60: 0 | S60: 0 | T60: 0 | U60: -2.99 | V60: 0 | W60: 2.99 | X60: 0 | Z60: 0 | AA60: 0 | AB60: 0 | AC60: 2.99 | AD60: 0 | AE60: 0 | AF60: -8.37 | AG60: 1.4 | AH60: -0.73 | AI60: -9.1 | AK60: 38c54130-77ff-4c05-8280-3466e1284b01 | AL60: ch_3SrO30GOs2bxG0Rw1kgJVYu9 | AM60: txn_3SrO30GOs2bxG0Rw1dYqUWdB | AN60: Self Delivery / 3PL
A61: 20/01/2026 | B61: 20/01/2026 | C61: Loughton | D61: Pickup | E61: Scheduled same day | F61: fulfilled | G61: WCTJW6 | H61: 16.94 | I61: 16.94 | J61: 22.45 | K61: 0 | L61: -6.5 | M61: 15.95 | N61: 0 | O61: 0.99 | P61: 0.16 | Q61: 0 | R61: 0 | S61: 0 | T61: 0 | U61: 0 | V61: 0 | W61: 0 | X61: 0 | Y61: CRISPY6 | Z61: 0 | AA61: 0 | AB61: 0 | AC61: 0 | AD61: 0 | AE61: 0 | AF61: -3.83 | AG61: 0.64 | AH61: -0.44 | AI61: -4.27 | AL61: ch_3SrjinGOs2bxG0Rw1g9AvT1C | AM61: txn_3SrjinGOs2bxG0Rw11juUAG3 | AN61: Self Delivery / 3PL
A62: 21/01/2026 | B62: 21/01/2026 | C62: Loughton | D62: Pickup | E62: Scheduled same day | F62: fulfilled | G62: FF7KK5 | H62: 24.89 | I62: 24.89 | J62: 23.9 | K62: 0 | L62: 0 | M62: 23.9 | N62: 0 | O62: 0.99 | P62: 0.16 | Q62: 0 | R62: 0 | S62: 0 | T62: 0 | U62: 0 | V62: 0 | W62: 0 | X62: 0 | Z62: 0 | AA62: 0 | AB62: 0 | AC62: 0 | AD62: 0 | AE62: 0 | AF62: -5.74 | AG62: 0.96 | AH62: -0.55 | AI62: -6.29 | AL62: ch_3SrzNQGOs2bxG0Rw0G7OphvS | AM62: txn_3SrzNQGOs2bxG0Rw01jAh84V | AN62: Self Delivery / 3PL
A63: 21/01/2026 | B63: 21/01/2026 | C63: Bethnal Green | D63: Delivery | E63: ASAP | F63: fulfilled | G63: 7PV462 | H63: 15.53 | I63: 15.53 | J63: 16.5 | K63: 0 | L63: -4.95 | M63: 11.55 | N63: 0 | O63: 0.99 | P63: 0.16 | Q63: 0 | R63: 0 | S63: -8.82 | T63: 1.47 | U63: 0 | V63: 0 | W63: 2.99 | X63: 5.83 | Y63: JERRELLSHACK3 | Z63: 0 | AA63: 0 | AB63: 0 | AC63: 2.99 | AD63: 0.5 | AE63: 5.83 | AF63: -2.78 | AG63: 0.46 | AH63: -0.42 | AI63: -12.02 | AK63: a86d2626-2c57-459b-bbda-2ef5bea7f64b | AL63: ch_3Ss4GRGOs2bxG0Rw02N8Jlll | AM63: txn_3Ss4GRGOs2bxG0Rw0syYz3L6 | AN63: Slerp Courier Partner - Bike/Moped
A64: 21/01/2026 | B64: 21/01/2026 | C64: Loughton | D64: Pickup | E64: Scheduled same day | F64: fulfilled | G64: THX4ZW | H64: 34.47 | I64: 34.47 | J64: 38.48 | K64: 0 | L64: -5 | M64: 33.48 | N64: 0 | O64: 0.99 | P64: 0.16 | Q64: 0 | R64: 0 | S64: 0 | T64: 0 | U64: 0 | V64: 0 | W64: 0 | X64: 0 | Y64: 3ZYLMG | Z64: 0 | AA64: 0 | AB64: 0 | AC64: 0 | AD64: 0 | AE64: 0 | AF64: -8.04 | AG64: 1.34 | AH64: -0.68 | AI64: -8.72 | AL64: ch_3Ss5OyGOs2bxG0Rw0M5EgsxD | AM64: txn_3Ss5OyGOs2bxG0Rw0hzV1rv6 | AN64: Self Delivery / 3PL
A65: 21/01/2026 | B65: 21/01/2026 | C65: Loughton | D65: Pickup | E65: ASAP | F65: fulfilled | G65: TZBLEZ | H65: 22.49 | I65: 22.49 | J65: 21.5 | K65: 0 | L65: 0 | M65: 21.5 | N65: 0 | O65: 0.99 | P65: 0.16 | Q65: 0 | R65: 0 | S65: 0 | T65: 0 | U65: 0 | V65: 0 | W65: 0 | X65: 0 | Z65: 0 | AA65: 0 | AB65: 0 | AC65: 0 | AD65: 0 | AE65: 0 | AF65: -5.16 | AG65: 0.86 | AH65: -0.51 | AI65: -5.67 | AL65: ch_3Ss5j2GOs2bxG0Rw0lJmrgYr | AM65: txn_3Ss5j2GOs2bxG0Rw0zt9OQTl | AN65: Self Delivery / 3PL
A66: 21/01/2026 | B66: 21/01/2026 | C66: Loughton | D66: Pickup | E66: Scheduled same day | F66: fulfilled | G66: TSBDBA | H66: 38.84 | I66: 38.84 | J66: 44.35 | K66: 0 | L66: -6.5 | M66: 37.85 | N66: 0 | O66: 0.99 | P66: 0.16 | Q66: 0 | R66: 0 | S66: 0 | T66: 0 | U66: 0 | V66: 0 | W66: 0 | X66: 0 | Y66: CRISPY6 | Z66: 0 | AA66: 0 | AB66: 0 | AC66: 0 | AD66: 0 | AE66: 0 | AF66: -9.09 | AG66: 1.52 | AH66: -1.33 | AI66: -10.42 | AL66: ch_3Ss5roGOs2bxG0Rw0AID20At | AM66: txn_3Ss5roGOs2bxG0Rw0c6Y3yM3 | AN66: Self Delivery / 3PL
A67: 21/01/2026 | B67: 21/01/2026 | C67: Maidstone | D67: Delivery | E67: Scheduled same day | F67: fulfilled | G67: EEDV4A | H67: 17.64 | I67: 17.64 | J67: 20.45 | K67: 0 | L67: -6.5 | M67: 13.95 | N67: 0 | O67: 0 | P67: 0 | Q67: 0.7 | R67: 0 | S67: 0 | T67: 0 | U67: -2.99 | V67: 0 | W67: 2.99 | X67: 0 | Y67: CRISPY6 | Z67: 0 | AA67: 0 | AB67: 0 | AC67: 2.99 | AD67: 0 | AE67: 0 | AF67: -3.35 | AG67: 0.56 | AH67: -0.45 | AI67: -3.8 | AK67: c9ef052d-5d79-4a2d-8ba6-c0d8799feaf0 | AL67: ch_3Ss6W0GOs2bxG0Rw1St2q5BK | AM67: txn_3Ss6W0GOs2bxG0Rw1u6ACIEr | AN67: Self Delivery / 3PL
A68: 21/01/2026 | B68: 21/01/2026 | C68: Maidstone | D68: Pickup | E68: Scheduled same day | F68: fulfilled | G68: 2P7WSS | H68: 21.45 | I68: 21.45 | J68: 27.95 | K68: 0 | L68: -6.5 | M68: 21.45 | N68: 0 | O68: 0 | P68: 0 | Q68: 0 | R68: 0 | S68: 0 | T68: 0 | U68: 0 | V68: 0 | W68: 0 | X68: 0 | Y68: CRISPY6 | Z68: 0 | AA68: 0 | AB68: 0 | AC68: 0 | AD68: 0 | AE68: 0 | AF68: -5.15 | AG68: 0.86 | AH68: -0.5 | AI68: -5.65 | AL68: ch_3Ss6XpGOs2bxG0Rw01eA9QYK | AM68: txn_3Ss6XpGOs2bxG0Rw0ggnlDvq | AN68: Self Delivery / 3PL
A69: 21/01/2026 | B69: 21/01/2026 | C69: Loughton | D69: Pickup | E69: ASAP | F69: fulfilled | G69: ZLABSA | H69: 28.89 | I69: 28.89 | J69: 27.9 | K69: 0 | L69: 0 | M69: 27.9 | N69: 0 | O69: 0.99 | P69: 0.16 | Q69: 0 | R69: 0 | S69: 0 | T69: 0 | U69: 0 | V69: 0 | W69: 0 | X69: 0 | Z69: 0 | AA69: 0 | AB69: 0 | AC69: 0 | AD69: 0 | AE69: 0 | AF69: -6.7 | AG69: 1.12 | AH69: -0.6 | AI69: -7.3 | AL69: ch_3Ss6o0GOs2bxG0Rw0nqsYd2c | AM69: txn_3Ss6o0GOs2bxG0Rw0LC1fppI | AN69: Self Delivery / 3PL
A70: 21/01/2026 | B70: 21/01/2026 | C70: Loughton | D70: Pickup | E70: ASAP | F70: fulfilled | G70: D5W4VR | H70: 14.94 | I70: 14.94 | J70: 13.95 | K70: 0 | L70: 0 | M70: 13.95 | N70: 0 | O70: 0.99 | P70: 0.16 | Q70: 0 | R70: 0 | S70: 0 | T70: 0 | U70: 0 | V70: 0 | W70: 0 | X70: 0 | Z70: 0 | AA70: 0 | AB70: 0 | AC70: 0 | AD70: 0 | AE70: 0 | AF70: -3.35 | AG70: 0.56 | AH70: -0.41 | AI70: -3.76 | AL70: ch_3Ss6q0GOs2bxG0Rw0x3Fo80Y | AM70: txn_3Ss6q0GOs2bxG0Rw0gvJHXvK | AN70: Self Delivery / 3PL
A71: 21/01/2026 | B71: 21/01/2026 | C71: Loughton | D71: Pickup | E71: ASAP | F71: fulfilled | G71: 4ZKG2N | H71: 13.26 | I71: 13.26 | J71: 20.45 | K71: 0 | L71: -8.18 | M71: 12.27 | N71: 0 | O71: 0.99 | P71: 0.16 | Q71: 0 | R71: 0 | S71: 0 | T71: 0 | U71: 0 | V71: 0 | W71: 0 | X71: 0 | Y71: WINGMASTER40 | Z71: 0 | AA71: 0 | AB71: 0 | AC71: 0 | AD71: 0 | AE71: 0 | AF71: -2.95 | AG71: 0.49 | AH71: -0.39 | AI71: -3.34 | AL71: ch_3Ss6pEGOs2bxG0Rw1snPS2tB | AM71: txn_3Ss6pEGOs2bxG0Rw1lNAqTIk | AN71: Self Delivery / 3PL
A72: 21/01/2026 | B72: 21/01/2026 | C72: Loughton | D72: Pickup | E72: Scheduled same day | F72: fulfilled | G72: EYLEST | H72: 13.99 | I72: 13.99 | J72: 17.75 | K72: 0 | L72: -4.75 | M72: 13 | N72: 0 | O72: 0.99 | P72: 0.16 | Q72: 0 | R72: 0 | S72: 0 | T72: 0 | U72: 0 | V72: 0 | W72: 0 | X72: 0 | Y72: BRXYGL | Z72: 0 | AA72: 0 | AB72: 0 | AC72: 0 | AD72: 0 | AE72: 0 | AF72: -3.12 | AG72: 0.52 | AH72: -0.4 | AI72: -3.52 | AL72: ch_3Ss86sGOs2bxG0Rw04khYmRT | AM72: txn_3Ss86sGOs2bxG0Rw0gILEoNi | AN72: Self Delivery / 3PL
A73: 24/01/2026 | B73: 24/01/2026 | C73: Loughton | D73: Pickup | E73: Scheduled same day | F73: fulfilled | G73: KHBJYV | H73: 30.09 | I73: 30.09 | J73: 29.1 | K73: 0 | L73: 0 | M73: 29.1 | N73: 0 | O73: 0.99 | P73: 0.16 | Q73: 0 | R73: 0 | S73: 0 | T73: 0 | U73: 0 | V73: 0 | W73: 0 | X73: 0 | Z73: 0 | AA73: 0 | AB73: 0 | AC73: 0 | AD73: 0 | AE73: 0 | AF73: -6.99 | AG73: 1.16 | AH73: -0.62 | AI73: -7.61 | AL73: ch_3StB7oGOs2bxG0Rw067ttV4K | AM73: txn_3StB7oGOs2bxG0Rw0fm25clS | AN73: Self Delivery / 3PL
A74: 24/01/2026 | B74: 24/01/2026 | C74: Loughton | D74: Delivery | E74: Scheduled same day | F74: fulfilled | G74: RPDGZ2 | H74: 16.43 | I74: 16.43 | J74: 15.44 | K74: 0 | L74: 0 | M74: 15.44 | N74: 0 | O74: 0.99 | P74: 0.16 | Q74: 0 | R74: 0 | S74: -13.56 | T74: 2.26 | U74: 0 | V74: 0 | W74: 6.99 | X74: 6.57 | Y74: FREEDELIVERYALLWEEEKEND | Z74: -6.99 | AA74: 0 | AB74: 0 | AC74: 0 | AD74: 0 | AE74: 13.56 | AF74: -3.71 | AG74: 0.62 | AH74: -0.43 | AI74: -17.7 | AK74: 1ae216e7-8bb2-4d22-b21d-d15ac5d36c53 | AL74: ch_3StBj7GOs2bxG0Rw1mrT2KHl | AM74: txn_3StBj7GOs2bxG0Rw1lSYbPd6 | AN74: Slerp Courier Partner - Car/Van
A75: 24/01/2026 | B75: 24/01/2026 | C75: Loughton | D75: Pickup | E75: Scheduled same day | F75: fulfilled | G75: RKUPCB | H75: 13.44 | I75: 13.44 | J75: 12.45 | K75: 0 | L75: 0 | M75: 12.45 | N75: 0 | O75: 0.99 | P75: 0.16 | Q75: 0 | R75: 0 | S75: 0 | T75: 0 | U75: 0 | V75: 0 | W75: 0 | X75: 0 | Z75: 0 | AA75: 0 | AB75: 0 | AC75: 0 | AD75: 0 | AE75: 0 | AF75: -2.99 | AG75: 0.5 | AH75: -0.39 | AI75: -3.38 | AL75: ch_3StC2qGOs2bxG0Rw1I1yrAkb | AM75: txn_3StC2qGOs2bxG0Rw11FqPHVo | AN75: Self Delivery / 3PL
A76: 25/01/2026 | B76: 25/01/2026 | C76: Loughton | D76: Delivery | E76: ASAP | F76: fulfilled | G76: WTQFGT | H76: 42.44 | I76: 42.44 | J76: 41.45 | K76: 0 | L76: 0 | M76: 41.45 | N76: 0 | O76: 0.99 | P76: 0.16 | Q76: 0 | R76: 0 | S76: -7.14 | T76: 1.19 | U76: 0 | V76: 0 | W76: 2.99 | X76: 4.15 | Y76: FREEDELIVERYALLWEEEKEND | Z76: -2.99 | AA76: 0 | AB76: 0 | AC76: 0 | AD76: 0 | AE76: 7.14 | AF76: -9.95 | AG76: 1.66 | AH76: -0.79 | AI76: -17.88 | AK76: 2b486dd3-e62c-4cf0-b940-0514416cc2c4 | AL76: ch_3StZHHGOs2bxG0Rw0bYmU2Yk | AM76: txn_3StZHHGOs2bxG0Rw0SkeF5xE | AN76: Slerp Courier Partner - Bike/Moped
A77: 25/01/2026 | B77: 25/01/2026 | C77: Loughton | D77: Delivery | E77: ASAP | F77: fulfilled | G77: 2GH2RY | H77: 16.24 | I77: 16.24 | J77: 15.25 | K77: 0 | L77: 0 | M77: 15.25 | N77: 0 | O77: 0.99 | P77: 0.16 | Q77: 0 | R77: 0 | S77: -13.56 | T77: 2.26 | U77: 0 | V77: 0 | W77: 6.99 | X77: 6.57 | Y77: FREEDELIVERYALLWEEEKEND | Z77: -6.99 | AA77: 0 | AB77: 0 | AC77: 0 | AD77: 0 | AE77: 13.56 | AF77: -3.66 | AG77: 0.61 | AH77: -0.67 | AI77: -17.89 | AK77: 6e934ae8-d218-4d41-a4be-0f31eea07a60 | AL77: ch_3StaSrGOs2bxG0Rw1CeuBA0o | AM77: txn_3StaSrGOs2bxG0Rw1yyWhRRC | AN77: Slerp Courier Partner - Bike/Moped
A78: 27/01/2026 | B78: 27/01/2026 | C78: Loughton | D78: Pickup | E78: Scheduled same day | F78: fulfilled | G78: F7ZDJ4 | H78: 22.59 | I78: 22.59 | J78: 21.6 | K78: 0 | L78: 0 | M78: 21.6 | N78: 0 | O78: 0.99 | P78: 0.16 | Q78: 0 | R78: 0 | S78: 0 | T78: 0 | U78: 0 | V78: 0 | W78: 0 | X78: 0 | Z78: 0 | AA78: 0 | AB78: 0 | AC78: 0 | AD78: 0 | AE78: 0 | AF78: -5.19 | AG78: 0.86 | AH78: -0.52 | AI78: -5.71 | AL78: ch_3SuGOUGOs2bxG0Rw0Wpn9kvp | AM78: txn_3SuGOUGOs2bxG0Rw0WKxfPlC | AN78: Self Delivery / 3PL
A79: 28/01/2026 | B79: 28/01/2026 | C79: Loughton | D79: Pickup | E79: ASAP | F79: fulfilled | G79: S7QHK5 | H79: 9.94 | I79: 9.94 | J79: 13.95 | K79: 0 | L79: -5 | M79: 8.95 | N79: 0 | O79: 0.99 | P79: 0.16 | Q79: 0 | R79: 0 | S79: 0 | T79: 0 | U79: 0 | V79: 0 | W79: 0 | X79: 0 | Y79: NNE27G | Z79: 0 | AA79: 0 | AB79: 0 | AC79: 0 | AD79: 0 | AE79: 0 | AF79: -2.15 | AG79: 0.36 | AH79: -0.34 | AI79: -2.49 | AL79: ch_3SuXo3GOs2bxG0Rw08VZZtR9 | AM79: txn_3SuXo3GOs2bxG0Rw0ajRSu2Z | AN79: Self Delivery / 3PL
A80: 28/01/2026 | B80: 28/01/2026 | C80: Loughton | D80: Pickup | E80: Scheduled same day | F80: fulfilled | G80: BUJNLD | H80: 20.49 | I80: 20.49 | J80: 19.5 | K80: 0 | L80: 0 | M80: 19.5 | N80: 0 | O80: 0.99 | P80: 0.16 | Q80: 0 | R80: 0 | S80: 0 | T80: 0 | U80: 0 | V80: 0 | W80: 0 | X80: 0 | Z80: 0 | AA80: 0 | AB80: 0 | AC80: 0 | AD80: 0 | AE80: 0 | AF80: -4.68 | AG80: 0.78 | AH80: -0.49 | AI80: -5.17 | AL80: ch_3SuYMtGOs2bxG0Rw0t7wuzOT | AM80: txn_3SuYMtGOs2bxG0Rw0lvgrTZ5 | AN80: Self Delivery / 3PL
A81: 28/01/2026 | B81: 28/01/2026 | C81: Maidstone | D81: Pickup | E81: Scheduled same day | F81: fulfilled | G81: QWKLYX | H81: 13 | I81: 13 | J81: 13 | K81: 0 | L81: 0 | M81: 13 | N81: 0 | O81: 0 | P81: 0 | Q81: 0 | R81: 0 | S81: 0 | T81: 0 | U81: 0 | V81: 0 | W81: 0 | X81: 0 | Z81: 0 | AA81: 0 | AB81: 0 | AC81: 0 | AD81: 0 | AE81: 0 | AF81: -3.12 | AG81: 0.52 | AH81: -0.38 | AI81: -3.5 | AL81: ch_3SuaBJGOs2bxG0Rw0FcV1epz | AM81: txn_3SuaBJGOs2bxG0Rw0vSpFnB8 | AN81: Self Delivery / 3PL
A82: 28/01/2026 | B82: 28/01/2026 | C82: Loughton | D82: Pickup | E82: ASAP | F82: fulfilled | G82: CSA6QJ | H82: 13.99 | I82: 13.99 | J82: 19.5 | K82: 0 | L82: -6.5 | M82: 13 | N82: 0 | O82: 0.99 | P82: 0.16 | Q82: 0 | R82: 0 | S82: 0 | T82: 0 | U82: 0 | V82: 0 | W82: 0 | X82: 0 | Y82: CRISPY6 | Z82: 0 | AA82: 0 | AB82: 0 | AC82: 0 | AD82: 0 | AE82: 0 | AF82: -3.12 | AG82: 0.52 | AH82: -0.4 | AI82: -3.52 | AL82: ch_3SubTMGOs2bxG0Rw1tFmTt0x | AM82: txn_3SubTMGOs2bxG0Rw1k89cO34 | AN82: Self Delivery / 3PL
A83: 28/01/2026 | B83: 28/01/2026 | C83: Loughton | D83: Pickup | E83: ASAP | F83: fulfilled | G83: WLSVQR | H83: 17.19 | I83: 17.19 | J83: 16.2 | K83: 0 | L83: 0 | M83: 16.2 | N83: 0 | O83: 0.99 | P83: 0.16 | Q83: 0 | R83: 0 | S83: 0 | T83: 0 | U83: 0 | V83: 0 | W83: 0 | X83: 0 | Z83: 0 | AA83: 0 | AB83: 0 | AC83: 0 | AD83: 0 | AE83: 0 | AF83: -3.89 | AG83: 0.65 | AH83: -0.44 | AI83: -4.33 | AL83: ch_3SudLBGOs2bxG0Rw1mA6L1sg | AM83: txn_3SudLBGOs2bxG0Rw14usYAQB | AN83: Self Delivery / 3PL
A84: 28/01/2026 | B84: 28/01/2026 | C84: Loughton | D84: Delivery | E84: ASAP | F84: fulfilled | G84: 5NQECW | H84: 16.98 | I84: 16.98 | J84: 13 | K84: 0 | L84: 0 | M84: 13 | N84: 0 | O84: 0.99 | P84: 0.16 | Q84: 0 | R84: 0 | S84: -7.98 | T84: 1.33 | U84: 0 | V84: 0 | W84: 2.99 | X84: 4.99 | Z84: 0 | AA84: 0 | AB84: 0 | AC84: 2.99 | AD84: 0.5 | AE84: 4.99 | AF84: -3.12 | AG84: 0.52 | AH84: -0.44 | AI84: -11.54 | AK84: ea907f25-d179-4f1c-a806-b2723ac61030 | AL84: ch_3SuddbGOs2bxG0Rw0ZVDHtkg | AM84: txn_3SuddbGOs2bxG0Rw0sCFnxmz | AN84: Slerp Courier Partner - Bike/Moped
A85: 28/01/2026 | B85: 28/01/2026 | C85: Maidstone | D85: Delivery | E85: Scheduled same day | F85: fulfilled | G85: 7TAGQP | H85: 22.64 | I85: 22.64 | J85: 19.65 | K85: 0 | L85: 0 | M85: 19.65 | N85: 0 | O85: 0 | P85: 0 | Q85: 0 | R85: 0 | S85: 0 | T85: 0 | U85: -2.99 | V85: 0 | W85: 2.99 | X85: 0 | Z85: 0 | AA85: 0 | AB85: 0 | AC85: 2.99 | AD85: 0 | AE85: 0 | AF85: -4.72 | AG85: 0.79 | AH85: -0.52 | AI85: -5.24 | AK85: c0444362-edd2-4a17-98e0-95d2c88e6223 | AL85: ch_3Sue4AGOs2bxG0Rw0yymSN1l | AM85: txn_3Sue4AGOs2bxG0Rw0gBb5nkb | AN85: Self Delivery / 3PL
A86: 30/01/2026 | B86: 30/01/2026 | C86: Loughton | D86: Pickup | E86: Scheduled same day | F86: fulfilled | G86: RJYHQY | H86: 28.79 | I86: 28.79 | J86: 27.8 | K86: 0 | L86: 0 | M86: 27.8 | N86: 0 | O86: 0.99 | P86: 0.16 | Q86: 0 | R86: 0 | S86: 0 | T86: 0 | U86: 0 | V86: 0 | W86: 0 | X86: 0 | Z86: 0 | AA86: 0 | AB86: 0 | AC86: 0 | AD86: 0 | AE86: 0 | AF86: -6.68 | AG86: 1.11 | AH86: -0.6 | AI86: -7.28 | AL86: ch_3SvLnjGOs2bxG0Rw0RZyn00x | AM86: txn_3SvLnjGOs2bxG0Rw065b4lna | AN86: Self Delivery / 3PL
A87: 31/01/2026 | B87: 31/01/2026 | C87: Maidstone | D87: Delivery | E87: Scheduled same day | F87: fulfilled | G87: PHPSH5 | H87: 41.44 | I87: 41.44 | J87: 43.95 | K87: 0 | L87: -6.5 | M87: 37.45 | N87: 0 | O87: 0 | P87: 0 | Q87: 0 | R87: 0 | S87: 0 | T87: 0 | U87: -3.99 | V87: 0 | W87: 3.99 | X87: 0 | Y87: CRISPY6 | Z87: 0 | AA87: 0 | AB87: 0 | AC87: 3.99 | AD87: 0 | AE87: 0 | AF87: -8.99 | AG87: 1.5 | AH87: -0.78 | AI87: -9.77 | AK87: 24e16596-056c-4b26-96cd-c2153bcfef03 | AL87: ch_3SvcuPGOs2bxG0Rw0592yawb | AM87: txn_3SvcuPGOs2bxG0Rw0gqyAWRh | AN87: Self Delivery / 3PL
A88: 31/01/2026 | B88: 31/01/2026 | C88: Loughton | D88: Delivery | E88: ASAP | F88: fulfilled | G88: LPQDEY | H88: 31.18 | I88: 31.18 | J88: 25.9 | K88: 0 | L88: 0 | M88: 25.9 | N88: 0 | O88: 0.99 | P88: 0.16 | Q88: 1.3 | R88: 0 | S88: -8.82 | T88: 1.47 | U88: 0 | V88: 0 | W88: 2.99 | X88: 5.83 | Z88: 0 | AA88: 0 | AB88: 0 | AC88: 2.99 | AD88: 0.5 | AE88: 5.83 | AF88: -6.22 | AG88: 1.04 | AH88: -0.64 | AI88: -15.68 | AK88: 021534e4-a28c-4551-ba02-c3ad36a2e3ff | AL88: ch_3SvkFlGOs2bxG0Rw0FA4wuJ2 | AM88: txn_3SvkFlGOs2bxG0Rw0RnLgM83 | AN88: Slerp Courier Partner - Car/Van
A89: 31/01/2026 | B89: 31/01/2026 | C89: Maidstone | D89: Delivery | E89: ASAP | F89: fulfilled | G89: 4F5UBD | H89: 34.34 | I89: 34.34 | J89: 37.85 | K89: 0 | L89: -6.5 | M89: 31.35 | N89: 0 | O89: 0 | P89: 0 | Q89: 0 | R89: 0 | S89: 0 | T89: 0 | U89: -2.99 | V89: 0 | W89: 2.99 | X89: 0 | Y89: CRISPY6 | Z89: 0 | AA89: 0 | AB89: 0 | AC89: 2.99 | AD89: 0 | AE89: 0 | AF89: -7.53 | AG89: 1.26 | AH89: -0.68 | AI89: -8.21 | AK89: 5fbb24d7-d8da-412b-a7f9-5fde0be6e827 | AL89: ch_3Svls4GOs2bxG0Rw0sUjfx5I | AM89: txn_3Svls4GOs2bxG0Rw0bdGmDiL | AN89: Self Delivery / 3PL
G90: Totals | H90: =SUM(H20:H89) | I90: =SUM(I20:I89) | J90: =SUM(J20:J89) | K90: =SUM(K20:K89) | L90: =SUM(L20:L89) | M90: =SUM(M20:M89) | N90: =SUM(N20:N89) | O90: =SUM(O20:O89) | ... W90: =SUM(W20:W89) | Y90: =SUM(Y20:Y89) | AA90: =SUM(AA20:AA89) | AB90: =SUM(AB20:AB89) | AC90: =SUM(AC20:AC89) | AD90: =SUM(AD20:AD89) | AE90: =SUM(AE20:AE89) | AF90: =SUM(AF20:AF89) | AG90: =SUM(AG20:AG89) | AH90: =SUM(AH20:AH89) | AI90: =SUM(AI20:AI89)
A92: Full Refunded/Rejected orders
A93: Order Date | B93: Fulfillment date | C93: Location name | D93: Fulfillment type | E93: Order type | F93: Status | G93: Slerp ref (Id) | H93: Gross transaction value | I93: Gross Transaction value (after refunds) | J93: Product total | K93: Product VAT component | L93: Product discount applied | M93: Product total after discounts (GMV)** | N93: Gifting charge | O93: Additional store fee | P93: VAT component of Additional store fee | Q93: Tips | R93: Refunds | S93: (A) Slerp Courier Partner Quoted Courier Fee Including Vat | T93: VAT component of Slerp Courier Partner Quoted Courier Fee | U93: Self-delivery Fee / Self-organised Fee including VAT | V93: VAT component of Self-delivery / Self-organised fee | W93: Delivery fees (charged to customer) pre-discount applied | X93: Delivery Subsidisation (charged to partner) pre-discount applied | Y93: Discount code | Z93: Delivery fee discount applied | AA93: Tiered Delivery pricing percent % | AB93: Tiered Delivery actual | AC93: Delivery fees (charged to customer) post-discount applied | AD93: VAT component of Delivery fees (charged to customer) post-discount applied | AE93: Delivery Subsidisation (charged to partner) post-discount applied | AF93: (B) Slerp Commission including VAT | AG93: VAT component of Slerp Commission | AH93: (C) Payment fee | AI93: Total Captured by Slerp (A) + (B) + (C) | AJ93: Notes | AK93: Courier reference | AL93: Stripe payment reference | AM93: Balance transaction (Id) | AN93: Courier Type
A94: 14/01/2026 | B94: 14/01/2026 | C94: Bethnal Green | D94: Delivery | E94: ASAP | F94: refunded | G94: U23AHY | H94: 11.48 | I94: 0 | J94: 10 | K94: 1.0833333 | L94: -2.5 | M94: 7.5 | N94: 0 | O94: 0.99 | P94: 0.16 | Q94: 0 | R94: -11.48 | S94: -8.82 | T94: 1.47 | U94: -8.82 | V94: 0 | W94: 2.99 | X94: 5.83 | Y94: jerrelshack1 | Z94: 0 | AA94: 0 | AB94: 0 | AC94: 2.99 | AD94: 0.5 | AE94: 5.83 | AF94: -1.8 | AG94: 0.3 | AH94: -0.36 | AI94: -10.98 | AK94: 6023c9f5-b6d3-460d-a4e2-9d7488f8c160 | AL94: ch_3SpV6zGOs2bxG0Rw1r82A3Z1 | AM94: txn_3SpV6zGOs2bxG0Rw1AgAt98c | AN94: Self Delivery / 3PL
A95: 16/01/2026 | B95: 16/01/2026 | C95: Bethnal Green | D95: Delivery | E95: ASAP | F95: rejected | G95: TSU3YN | H95: 15.53 | I95: 0 | J95: 16.5 | K95: 0 | L95: -4.95 | M95: 11.55 | N95: 0 | O95: 0.99 | P95: 0.16 | Q95: 0 | R95: -15.53 | S95: -8.82 | T95: 1.47 | U95: -8.82 | V95: 0 | W95: 2.99 | X95: 5.83 | Y95: JERRELLSHACK2 | Z95: 0 | AA95: 0 | AB95: 0 | AC95: 2.99 | AD95: 0.5 | AE95: 5.83 | AF95: -2.78 | AG95: 0.46 | AH95: -0.42 | AI95: -12.02 | AL95: ch_3SqCxrGOs2bxG0Rw19xiGyaL | AM95: txn_3SqCxrGOs2bxG0Rw14WHiYqj | AN95: Self Delivery / 3PL
A96: 18/01/2026 | B96: 18/01/2026 | C96: Luton | D96: Delivery | E96: ASAP | F96: fulfilled | G96: 5RBFEN | H96: 27.13 | I96: 0 | J96: 29.65 | K96: 4.9416667 | L96: -6.5 | M96: 23.15 | N96: 0 | O96: 0.99 | P96: 0.16 | Q96: 0 | R96: -27.13 | S96: -7.14 | T96: 1.19 | U96: -7.14 | V96: 0 | W96: 2.99 | X96: 4.15 | Y96: CRISPY6 | Z96: 0 | AA96: 0 | AB96: 0 | AC96: 2.99 | AD96: 0.5 | AE96: 4.15 | AF96: -5.56 | AG96: 0.93 | AH96: -0.99 | AI96: -13.69 | AK96: 0f744f09-6bdf-4203-9786-784d5de5b051 | AL96: ch_3SqyIZGOs2bxG0Rw1meDpXWi | AM96: txn_3SqyIZGOs2bxG0Rw1FoDbyCB | AN96: Slerp Courier Partner - Bike/Moped
A97: 18/01/2026 | B97: 18/01/2026 | C97: Loughton | D97: Pickup | E97: Scheduled same day | F97: refunded | G97: 5YBD4D | H97: 16.24 | I97: 0 | J97: 15.25 | K97: 0 | L97: 0 | M97: 15.25 | N97: 0 | O97: 0.99 | P97: 0.16 | Q97: 0 | R97: -16.24 | S97: 0 | T97: 0 | U97: 0 | V97: 0 | W97: 0 | X97: 0 | Z97: 0 | AA97: 0 | AB97: 0 | AC97: 0 | AD97: 0 | AE97: 0 | AF97: -3.66 | AG97: 0.61 | AH97: -0.43 | AI97: -4.09 | AL97: ch_3Sqz4MGOs2bxG0Rw0c08qDtv | AM97: txn_3Sqz4MGOs2bxG0Rw0RmcvqdS | AN97: Self Delivery / 3PL
A98: 21/01/2026 | B98: 21/01/2026 | C98: Luton | D98: Pickup | E98: Scheduled same day | F98: accepted | G98: 2NLJBV | H98: 20.49 | I98: 20.49 | J98: 26 | K98: 4.3333333 | L98: -6.5 | M98: 19.5 | N98: 0 | O98: 0.99 | P98: 0.16 | Q98: 0 | R98: 0 | S98: 0 | T98: 0 | U98: 0 | V98: 0 | W98: 0 | X98: 0 | Y98: CRISPY6 | Z98: 0 | AA98: 0 | AB98: 0 | AC98: 0 | AD98: 0 | AE98: 0 | AF98: -4.68 | AG98: 0.78 | AH98: -0.49 | AI98: -5.17 | AL98: ch_3Ss67dGOs2bxG0Rw19t1Tzky | AM98: txn_3Ss67dGOs2bxG0Rw126t84kv | AN98: Self Delivery / 3PL
A99: 21/01/2026 | B99: 21/01/2026 | C99: Bethnal Green | D99: Delivery | E99: ASAP | F99: refunded | G99: QBBTW7 | H99: 15.28 | I99: 0 | J99: 11.3 | K99: 0 | L99: 0 | M99: 11.3 | N99: 0 | O99: 0.99 | P99: 0.16 | Q99: 0 | R99: -15.28 | S99: -8.82 | T99: 1.47 | U99: -8.82 | V99: 0 | W99: 2.99 | X99: 5.83 | Z99: 0 | AA99: 0 | AB99: 0 | AC99: 2.99 | AD99: 0.5 | AE99: 5.83 | AF99: -2.72 | AG99: 0.45 | AH99: -0.64 | AI99: -12.18 | AK99: 9698bbf2-1365-436d-998f-7e34aa97db8f | AL99: ch_3Ss6CGGOs2bxG0Rw0q4ltrYj | AM99: txn_3Ss6CGGOs2bxG0Rw0A5BHgvz | AN99: Slerp Courier Partner - Bike/Moped
A100: 23/01/2026 | B100: 23/01/2026 | C100: Luton | D100: Delivery | E100: ASAP | F100: fulfilled | G100: F4NJPJ | H100: 25.18 | I100: 0 | J100: 27.7 | K100: 4.6166667 | L100: -6.5 | M100: 21.2 | N100: 0 | O100: 0.99 | P100: 0.16 | Q100: 0 | R100: -25.18 | S100: -7.14 | T100: 1.19 | U100: -7.14 | V100: 0 | W100: 2.99 | X100: 4.15 | Y100: CRISPY6 | Z100: 0 | AA100: 0 | AB100: 0 | AC100: 2.99 | AD100: 0.5 | AE100: 4.15 | AF100: -5.09 | AG100: 0.85 | AH100: -0.55 | AI100: -12.78 | AK100: 6819fae7-640c-4b4b-8585-dc832b527a57 | AL100: ch_3Ssr1fGOs2bxG0Rw0A73L86i | AM100: txn_3Ssr1fGOs2bxG0Rw0ClvrmKb | AN100: Slerp Courier Partner - Bike/Moped
G101: Totals | H101: =SUM(H93:H100) | I101: =SUM(I93:I100) | J101: =SUM(J93:J100) | K101: =SUM(K93:K100) | L101: =SUM(L93:L100) | M101: =SUM(M93:M100) | N101: =SUM(N93:N100) | O101: =SUM(O93:O100) | ... W101: =SUM(W93:W100) | Y101: =SUM(Y93:Y100) | AA101: =SUM(AA93:AA100) | AB101: =SUM(AB93:AB100) | AC101: =SUM(AC93:AC100) | AD101: =SUM(AD93:AD100) | AE101: =SUM(AE93:AE100) | AF101: =SUM(AF93:AF100) | AG101: =SUM(AG93:AG100) | AH101: =SUM(AH93:AH100) | AI101: =SUM(AI93:AI100)
A103: Partial Refunded orders
A104: Order Date | B104: Fulfillment date | C104: Location name | D104: Fulfillment type | E104: Order type | F104: Status | G104: Slerp ref (Id) | H104: Gross transaction value | I104: Gross Transaction value (after refunds) | J104: Product total | K104: Product VAT component | L104: Product discount applied | M104: Product total after discounts (GMV)** | N104: Gifting charge | O104: Additional store fee | P104: VAT component of Additional store fee | Q104: Tips | R104: Refunds | S104: (A) Slerp Courier Partner Quoted Courier Fee Including Vat | T104: VAT component of Slerp Courier Partner Quoted Courier Fee | U104: Self-delivery Fee / Self-organised Fee including VAT | V104: VAT component of Self-delivery / Self-organised fee | W104: Delivery fees (charged to customer) pre-discount applied | X104: Delivery Subsidisation (charged to partner) pre-discount applied | Y104: Discount code | Z104: Delivery fee discount applied | AA104: Tiered Delivery pricing percent % | AB104: Tiered Delivery actual | AC104: Delivery fees (charged to customer) post-discount applied | AD104: VAT component of Delivery fees (charged to customer) post-discount applied | AE104: Delivery Subsidisation (charged to partner) post-discount applied | AF104: (B) Slerp Commission including VAT | AG104: VAT component of Slerp Commission | AH104: (C) Payment fee | AI104: Total Captured by Slerp (A) + (B) + (C) | AJ104: Notes | AK104: Courier reference | AL104: Stripe payment reference | AM104: Balance transaction (Id) | AN104: Courier Type
G105: Totals | H105: =SUM(H104:H104) | I105: =SUM(I104:I104) | J105: =SUM(J104:J104) | K105: =SUM(K104:K104) | L105: =SUM(L104:L104) | M105: =SUM(M104:M104) | N105: =SUM(N104:N104) | O105: =SUM(O104:O104) | ... W105: =SUM(W104:W104) | Y105: =SUM(Y104:Y104) | AA105: =SUM(AA104:AA104) | AB105: =SUM(AB104:AB104) | AC105: =SUM(AC104:AC104) | AD105: =SUM(AD104:AD104) | AE105: =SUM(AE104:AE104) | AF105: =SUM(AF104:AF104) | AG105: =SUM(AG104:AG104) | AH105: =SUM(AH104:AH104) | AI105: =SUM(AI104:AI104)
A107: *Some Slerp Courier Partners charge VAT. This is the weighted average based on vehicle type and usage across the platform.

Sheet Summary
A1: This is a summary based on your download. Please note the period it reflects.
A2: This is not a VAT invoice. To see invoices and receipts, please login in to Controls > Settings > Accounts & Billing
D4: Generated on: 14 February 2026
A6: Period: | D6: January 1 to January 31
A9: Company name: | D9: Wing Shack Co
B10: NET | C10: VAT paid for Slerp | D10: Total
A11: Slerp Fees & Charges
A12: Slerp Commissions: | B12: =D12/1.2 | C12: =B12*0.2 | D12: =-'2026-01-01 to 2026-01-31'!C14
A13: Payment Fees (no VAT applicable): | B13: =D13 | C13: =0 | D13: =-'2026-01-01 to 2026-01-31'!C16
A14: Slerp Courier Partner Fees: | B14: =D14/1.2 | C14: =B14*0.2 | D14: =-'2026-01-01 to 2026-01-31'!C15
A15: Total Fees & Charges | B15: =SUM(B12:B14) | C15: =SUM(C12:C14) | D15: =SUM(D12:D14)
A17: Goods and Services | B17: NET | C17: VAT Collected | D17: Total
A18: Products: | B18: =D18-C18 | C18: ='2026-01-01 to 2026-01-31'!K90+'2026-01-01 to 2026-01-31'!K105 | D18: ='2026-01-01 to 2026-01-31'!M90+'2026-01-01 to 2026-01-31'!M105
A19: Self-delivery / Self-organised fees: | B19: =D19-C19 | C19: =SUM('2026-01-01 to 2026-01-31'!V90, '2026-01-01 to 2026-01-31'!V105) | D19: =-SUM('2026-01-01 to 2026-01-31'!U90, '2026-01-01 to 2026-01-31'!U105)
A20: Additional store fee: | B20: =D20-C20 | C20: =SUM('2026-01-01 to 2026-01-31'!P90, '2026-01-01 to 2026-01-31'!P105) | D20: =SUM('2026-01-01 to 2026-01-31'!O90, '2026-01-01 to 2026-01-31'!O105)
A21: Total Goods and Services: | B21: =SUM(B18:B20) | C21: =SUM(C18:C20) | D21: =SUM(D18:D20)
C27: Total VAT paid for Slerp | D27: =C15
C28: Total Vat Collected from End-Customer | D28: =C20
A30: *Figures may change based on when the Statement is generated as order statuses change. I.e. Refunds
A31: **Figures exclude fully refunded orders, additional post-transaction charges (i.e. additional courier charges), as well as monthly SaaS charges.
